{"nodes": [{"id": "src_utils_actions_wait_utils_ts", "label": "wait_utils.ts", "file_type": "code", "source_file": "src\\utils\\actions\\wait_utils.ts", "source_location": "L1"}, {"id": "wait_utils_boxedstep", "label": "boxedStep()", "file_type": "code", "source_file": "src\\utils\\actions\\wait_utils.ts", "source_location": "L20"}, {"id": "wait_utils_waitforpagestability", "label": "waitForPageStability()", "file_type": "code", "source_file": "src\\utils\\actions\\wait_utils.ts", "source_location": "L33"}], "edges": [{"source": "src_utils_actions_wait_utils_ts", "target": "test", "relation": "imports_from", "confidence": "EXTRACTED", "source_file": "src\\utils\\actions\\wait_utils.ts", "source_location": "L1", "weight": 1.0}, {"source": "src_utils_actions_wait_utils_ts", "target": "logger", "relation": "imports_from", "confidence": "EXTRACTED", "source_file": "src\\utils\\actions\\wait_utils.ts", "source_location": "L2", "weight": 1.0}, {"source": "src_utils_actions_wait_utils_ts", "target": "wait_utils_boxedstep", "relation": "contains", "confidence": "EXTRACTED", "source_file": "src\\utils\\actions\\wait_utils.ts", "source_location": "L20", "weight": 1.0}, {"source": "src_utils_actions_wait_utils_ts", "target": "wait_utils_waitforpagestability", "relation": "contains", "confidence": "EXTRACTED", "source_file": "src\\utils\\actions\\wait_utils.ts", "source_location": "L33", "weight": 1.0}, {"source": "wait_utils_waitforpagestability", "target": "wait_utils_boxedstep", "relation": "calls", "confidence": "EXTRACTED", "source_file": "src\\utils\\actions\\wait_utils.ts", "source_location": "L60", "weight": 1.0}], "raw_calls": [{"caller_nid": "wait_utils_boxedstep", "callee": "step", "source_file": "src\\utils\\actions\\wait_utils.ts", "source_location": "L26"}, {"caller_nid": "wait_utils_boxedstep", "callee": "fn", "source_file": "src\\utils\\actions\\wait_utils.ts", "source_location": "L29"}]}